kiji/__init__.py
kiji/article.py
kiji/extraction.py
kiji/inspection.py
kiji-0.0.4.dist-info/LICENSE.txt
kiji-0.0.4.dist-info/METADATA
kiji-0.0.4.dist-info/WHEEL
kiji-0.0.4.dist-info/top_level.txt
kiji-0.0.4.dist-info/RECORD
