Metadata-Version: 2.1
Name: kiji
Version: 0.0.4
Summary: A library for web article extraction
Home-page: https://github.com/wanasit/kiji
Author: Wanasit Tanakitrungruang
License: UNKNOWN
Project-URL: Bug Tracker, https://github.com/wanasit/kiji/issues
Platform: UNKNOWN
Classifier: Programming Language :: Python :: 3
Classifier: License :: OSI Approved :: MIT License
Classifier: Operating System :: OS Independent
Requires-Python: >=3.6
License-File: LICENSE.txt
Requires-Dist: beautifulsoup4
